sm_macro(aconst_null,0x01,1)
sm_macro(iconst_m1,0x02,1)
sm_macro(iconst_0,0x03,1)
sm_macro(iconst_1,0x04,1)
sm_macro(iconst_2,0x05,1)
sm_macro(iconst_3,0x06,1)
sm_macro(iconst_4,0x07,1)
sm_macro(iconst_5,0x08,1)
sm_macro(lconst_0,0x09,1)
sm_macro(lconst_1,0x0A,1)
sm_macro(fconst_0,0x0B,1)
sm_macro(fconst_1,0x0C,1)
sm_macro(fconst_2,0x0D,1)
sm_macro(dconst_0,0x0E,1)
sm_macro(dconst_1,0x0F,1)
sm_macro(bipush,0x10,1)
sm_macro(sipush,0x11,1)
sm_macro(ldc,0x12,1)
sm_macro(ldc_w,0x13,1)
sm_macro(ldc2_w,0x14,1)
sm_macro(iload,0x15,1)
sm_macro(lload,0x16,1)
sm_macro(fload,0x17,1)
sm_macro(dload,0x18,1)
sm_macro(aload,0x19,1)
sm_macro(iload_0,0x1A,1)
sm_macro(iload_1,0x1B,1)
sm_macro(iload_2,0x1C,1)
sm_macro(iload_3,0x1D,1)
sm_macro(lload_0,0x1E,1)
sm_macro(lload_1,0x1F,1)
sm_macro(lload_2,0x20,1)
sm_macro(lload_3,0x21,1)
sm_macro(fload_0,0x22,1)
sm_macro(fload_1,0x23,1)
sm_macro(fload_2,0x24,1)
sm_macro(fload_3,0x25,1)
sm_macro(dload_0,0x26,1)
sm_macro(dload_1,0x27,1)
sm_macro(dload_2,0x28,1)
sm_macro(dload_3,0x29,1)
sm_macro(aload_1,0x2B,1)
sm_macro(aload_2,0x2C,1)
sm_macro(aload_3,0x2D,1)
sm_macro(iaload,0x2E,1)
sm_macro(laload,0x2F,1)
sm_macro(faload,0x30,1)
sm_macro(daload,0x31,1)
sm_macro(aaload,0x32,1)
sm_macro(baload,0x33,1)
sm_macro(caload,0x34,1)
sm_macro(saload,0x35,1)
sm_macro(istore,0x36,1)
sm_macro(lstore,0x37,1)
sm_macro(fstore,0x38,1)
sm_macro(dstore,0x39,1)
sm_macro(astore,0x3A,1)
sm_macro(istore_0,0x3B,1)
sm_macro(istore_1,0x3C,1)
sm_macro(istore_2,0x3D,1)
sm_macro(istore_3,0x3E,1)
sm_macro(lstore_0,0x3F,1)
sm_macro(lstore_1,0x40,1)
sm_macro(lstore_2,0x41,1)
sm_macro(lstore_3,0x42,1)
sm_macro(fstore_0,0x43,1)
sm_macro(fstore_1,0x44,1)
sm_macro(fstore_2,0x45,1)
sm_macro(fstore_3,0x46,1)
sm_macro(dstore_0,0x47,1)
sm_macro(dstore_1,0x48,1)
sm_macro(dstore_2,0x49,1)
sm_macro(dstore_3,0x4A,1)
sm_macro(astore_0,0x4B,1)
sm_macro(astore_1,0x4C,1)
sm_macro(astore_2,0x4D,1)
sm_macro(astore_3,0x4E,1)
sm_macro(iastore,0x4F,1)
sm_macro(lastore,0x50,1)
sm_macro(fastore,0x51,1)
sm_macro(dastore,0x52,1)
sm_macro(aastore,0x53,1)
sm_macro(bastore,0x54,1)
sm_macro(castore,0x55,1)
sm_macro(sastore,0x56,1)
sm_macro(pop,0x57,1)
sm_macro(pop2,0x58,1)
sm_macro(dup_x1,0x5A,1)
sm_macro(dup_x2,0x5B,1)
sm_macro(dup2,0x5C,1)
sm_macro(dup2_x1,0x5D,1)
sm_macro(dup2_x2,0x5E,1)
sm_macro(swap,0x5F,1)
sm_macro(iadd,0x60,1)
sm_macro(ladd,0x61,1)
sm_macro(fadd,0x62,1)
sm_macro(dadd,0x63,1)
sm_macro(isub,0x64,1)
sm_macro(lsub,0x65,1)
sm_macro(fsub,0x66,1)
sm_macro(dsub,0x67,1)
sm_macro(imul,0x68,1)
sm_macro(lmul,0x69,1)
sm_macro(fmul,0x6A,1)
sm_macro(dmul,0x6B,1)
sm_macro(idiv,0x6C,1)
sm_macro(ldiv,0x6D,1)
sm_macro(fdiv,0x6E,1)
sm_macro(ddiv,0x6F,1)
sm_macro(irem,0x70,1)
sm_macro(lrem,0x71,1)
sm_macro(frem,0x72,1)
sm_macro(drem,0x73,1)
sm_macro(ineg,0x74,1)
sm_macro(lneg,0x75,1)
sm_macro(fneg,0x76,1)
sm_macro(dneg,0x77,1)
sm_macro(ishl,0x78,1)
sm_macro(lshl,0x79,1)
sm_macro(ishr,0x7A,1)
sm_macro(lshr,0x7B,1)
sm_macro(iushr,0x7C,1)
sm_macro(lushr,0x7D,1)
sm_macro(iand,0x7E,1)
sm_macro(land,0x7F,1)
sm_macro(ior,0x80,1)
sm_macro(lor,0x81,1)
sm_macro(ixor,0x82,1)
sm_macro(lxor,0x83,1)
sm_macro(iinc,0x84,1)
sm_macro(i2l,0x85,1)
sm_macro(i2f,0x86,1)
sm_macro(i2d,0x87,1)
sm_macro(l2i,0x88,1)
sm_macro(l2f,0x89,1)
sm_macro(l2d,0x8A,1)
sm_macro(f2i,0x8B,1)
sm_macro(f2l,0x8C,1)
sm_macro(f2d,0x8D,1)
sm_macro(d2i,0x8E,1)
sm_macro(d2l,0x8F,1)
sm_macro(d2f,0x90,1)
sm_macro(i2b,0x91,1)
sm_macro(i2c,0x92,1)
sm_macro(i2s,0x93,1)
sm_macro(lcmp,0x94,1)
sm_macro(fcmpl,0x95,1)
sm_macro(fcmpg,0x96,1)
sm_macro(dcmpl,0x97,1)
sm_macro(dcmpg,0x98,1)
sm_macro(ifeq,0x99,1)
sm_macro(ifne,0x9A,1)
sm_macro(iflt,0x9B,1)
sm_macro(ifge,0x9C,1)
sm_macro(ifgt,0x9D,1)
sm_macro(ifle,0x9E,1)
sm_macro(if_icmpeq,0x9F,1)
sm_macro(if_icmpne,0xA0,1)
sm_macro(if_icmplt,0xA1,1)
sm_macro(if_icmpge,0xA2,1)
sm_macro(if_icmpgt,0xA3,1)
sm_macro(if_icmple,0xA4,1)
sm_macro(if_acmpeq,0xA5,1)
sm_macro(if_acmpne,0xA6,1)
sm_macro(goto,0xA7,1)
sm_macro(jsr,0xA8,1)
sm_macro(ret,0xA9,1)
sm_macro(tableswitch,0xAA,1)
sm_macro(lookupswitch,0xAB,1)
sm_macro(ireturn,0xAC,1)
sm_macro(lreturn,0xAD,1)
sm_macro(freturn,0xAE,1)
sm_macro(dreturn,0xAF,1)
sm_macro(areturn,0xB0,1)
sm_macro(return,0xB1,1)
sm_macro(getstatic,0xB2,1)
sm_macro(putstatic,0xB3,1)
sm_macro(getfield,0xB4,1)
sm_macro(putfield,0xB5,1)
sm_macro(invokevirtual,0xB6,1)
sm_macro(invokespecial,0xB7,1)
sm_macro(invokestatic,0xB8,1)
sm_macro(invokeinterface,0xB9,1)
sm_macro(unused,0xBA,1)
sm_macro(newarray,0xBC,1)
sm_macro(anewarray,0xBD,1)
sm_macro(arraylength,0xBE,1)
sm_macro(athrow,0xBF,1)
sm_macro(checkcast,0xC0,1)
sm_macro(instanceof,0xC1,1)
sm_macro(monitorenter,0xC2,1)
sm_macro(monitorexit,0xC3,1)
sm_macro(wide,0xC4,1)
sm_macro(multianewarray,0xC5,1)
sm_macro(ifnull,0xC6,1)
sm_macro(ifnonnull,0xC7,1)
sm_macro(goto_w,0xC8,1)
sm_macro(jsr_w,0xC9,1)
sm_macro(breakpoint,0xCA,1)
sm_macro(impdep1,0xFE,1)
sm_macro(impdep2,0xFF,1)
